[
  {
    "page": 1,
    "line_no": 1,
    "text": "12 Jun Thu Students leave for the German Exchange program to Hittorf-Gymnasium"
  },
  {
    "page": 1,
    "line_no": 2,
    "text": "22 Jun Sun G PIE Conference begins"
  },
  {
    "page": 1,
    "line_no": 3,
    "text": "25 Jun Wed Inspection of the academic spaces by HM, DHM, Bursar, DEA"
  },
  {
    "page": 1,
    "line_no": 4,
    "text": "27 Jun Fri G PIE Conference concludes"
  },
  {
    "page": 1,
    "line_no": 5,
    "text": "28 Jun Sat Housemasters' Council Meeting"
  },
  {
    "page": 1,
    "line_no": 6,
    "text": "28 Jun Sat Inspection of the boarding houses by HM, DHM, Bursar, DEP"
  },
  {
    "page": 1,
    "line_no": 7,
    "text": "29 Jun Sun Staff meeting"
  },
  {
    "page": 1,
    "line_no": 8,
    "text": "30 Jun Mon Students return after Summer Vacation"
  },
  {
    "page": 1,
    "line_no": 9,
    "text": "1 Jul Tue Autumn Term 2025 begins"
  },
  {
    "page": 1,
    "line_no": 10,
    "text": "1 Jul Tue Delegation leaves for ISSC Hong Kong"
  },
  {
    "page": 1,
    "line_no": 11,
    "text": "1 Jul Tue School team leaves for IPSC Chess at Genesis Global School, Noida"
  },
  {
    "page": 1,
    "line_no": 12,
    "text": "2 Jul Wed July assessment begins"
  },
  {
    "page": 1,
    "line_no": 13,
    "text": "2 Jul Wed Students return from the German Exchange program"
  },
  {
    "page": 1,
    "line_no": 14,
    "text": "4 Jul Fri Academic Council Meeting"
  },
  {
    "page": 1,
    "line_no": 15,
    "text": "4 Jul Fri Yearbook photographs"
  },
  {
    "page": 1,
    "line_no": 16,
    "text": "5 Jul Sat Yearbook photographs"
  },
  {
    "page": 1,
    "line_no": 17,
    "text": "5 Jul Sat BSAI AGM"
  },
  {
    "page": 1,
    "line_no": 18,
    "text": "5 Jul Sat School team returns from IPSC Chess"
  },
  {
    "page": 1,
    "line_no": 19,
    "text": "5 Jul Sat Declaration of the results - IBDP 2025"
  },
  {
    "page": 2,
    "line_no": 1,
    "text": "6 Jul Sun NO OUTING"
  },
  {
    "page": 2,
    "line_no": 2,
    "text": "6 Jul Sun BSAI AGM"
  },
  {
    "page": 2,
    "line_no": 3,
    "text": "7 Jul Mon Delegation returns from ISSC"
  },
  {
    "page": 2,
    "line_no": 4,
    "text": "8 Jul Tue July assessment ends"
  },
  {
    "page": 2,
    "line_no": 5,
    "text": "9 Jul Wed Special Assembly"
  },
  {
    "page": 2,
    "line_no": 6,
    "text": "9 Jul Wed Gauss Exam"
  },
  {
    "page": 2,
    "line_no": 7,
    "text": "9 Jul Wed Senior Inter-house English Debate continues"
  },
  {
    "page": 2,
    "line_no": 8,
    "text": "10 Jul Thu Senior Inter-house English Debate Semi Final"
  },
  {
    "page": 2,
    "line_no": 9,
    "text": "11 Jul Fri Senior Inter-house English Debate Final"
  },
  {
    "page": 2,
    "line_no": 10,
    "text": "12 Jul Sat PD session for staff"
  },
  {
    "page": 2,
    "line_no": 11,
    "text": "12 Jul Sat Yearbook photographs"
  },
  {
    "page": 2,
    "line_no": 12,
    "text": "12 Jul Sat Inter-house Music and Dance: Band and Western Vocal"
  },
  {
    "page": 2,
    "line_no": 13,
    "text": "13 Jul Sun OUTING"
  },
  {
    "page": 2,
    "line_no": 14,
    "text": "13 Jul Sun Yearbook photographs"
  },
  {
    "page": 2,
    "line_no": 15,
    "text": "14 Jul Mon Junior Inter-house English Debate begins"
  },
  {
    "page": 2,
    "line_no": 16,
    "text": "14 Jul Mon Final submission for B.G.Pitre Science Fiction"
  },
  {
    "page": 2,
    "line_no": 17,
    "text": "15 Jul Tue Library Council meeting"
  },
  {
    "page": 2,
    "line_no": 18,
    "text": "15 Jul Tue Asset test for D and C form (English)"
  },
  {
    "page": 2,
    "line_no": 19,
    "text": "16 Jul Wed Workshop on Problem Solving for C form"
  },
  {
    "page": 2,
    "line_no": 20,
    "text": "16 Jul Wed Team leaves for IPSC IT Fest at B. K. Birla Centre for Education, Pune"
  },
  {
    "page": 2,
    "line_no": 21,
    "text": "17 Jul Thu IBDP Program Development Meeting"
  },
  {
    "page": 2,
    "line_no": 22,
    "text": "17 Jul Thu Asset test for D and C form (Math)"
  },
  {
    "page": 2,
    "line_no": 23,
    "text": "17 Jul Thu Workshop on Financial Literacy for B form"
  },
  {
    "page": 2,
    "line_no": 24,
    "text": "18 Jul Fri School Council meeting"
  },
  {
    "page": 2,
    "line_no": 25,
    "text": "18 Jul Fri Asset test for D and C form (Science)"
  },
  {
    "page": 3,
    "line_no": 1,
    "text": "19 Jul Sat PD session for staff"
  },
  {
    "page": 3,
    "line_no": 2,
    "text": "19 Jul Sat Tutorial Meeting"
  },
  {
    "page": 3,
    "line_no": 3,
    "text": "19 Jul Sat Inter-house Senior Quiz competition"
  },
  {
    "page": 3,
    "line_no": 4,
    "text": "19 Jul Sat Young Performers (Instrumental)"
  },
  {
    "page": 3,
    "line_no": 5,
    "text": "20 Jul Sun OUTING"
  },
  {
    "page": 3,
    "line_no": 6,
    "text": "20 Jul Sun In house training for Chairpersons and Deputy Chairpersons of DSMUN"
  },
  {
    "page": 3,
    "line_no": 7,
    "text": "20 Jul Sun Team returns from IPSC IT Fest"
  },
  {
    "page": 3,
    "line_no": 8,
    "text": "20 Jul Sun Call Over - Hyderabad House"
  },
  {
    "page": 3,
    "line_no": 9,
    "text": "21 Jul Mon Inter-house Hindi Debates (Sr) - First round"
  },
  {
    "page": 3,
    "line_no": 10,
    "text": "21 Jul Mon Workshop on Cyber Safety and Digital Wellbeing - B and S Form"
  },
  {
    "page": 3,
    "line_no": 11,
    "text": "22 Jul Tue Council meetings (Study, Pastoral, Tech, Co-curricular, IAYP)"
  },
  {
    "page": 3,
    "line_no": 12,
    "text": "22 Jul Tue Workshop on Cyber Safety and Digital Wellbeing - B and S Form"
  },
  {
    "page": 3,
    "line_no": 13,
    "text": "22 Jul Tue Team leaves for the Shri Debates at Shriram School, Moulsari"
  },
  {
    "page": 3,
    "line_no": 14,
    "text": "23 Jul Wed TOEFL"
  },
  {
    "page": 3,
    "line_no": 15,
    "text": "23 Jul Wed Junior Inter-house English Debate Finals"
  },
  {
    "page": 3,
    "line_no": 16,
    "text": "23 Jul Wed School team leaves for IPSC Basketball (Under 19) at The Mann School"
  },
  {
    "page": 3,
    "line_no": 17,
    "text": "24 Jul Thu Inter-house Hindi Debates (Sr) - Second round"
  },
  {
    "page": 3,
    "line_no": 18,
    "text": "24 Jul Thu Uttarakhand State shooting Championship-Dehradun"
  },
  {
    "page": 3,
    "line_no": 19,
    "text": "25 Jul Fri Inter-school Math Competition SIGMA"
  },
  {
    "page": 3,
    "line_no": 20,
    "text": "25 Jul Fri Inter-school Science competition ALPHA"
  },
  {
    "page": 3,
    "line_no": 21,
    "text": "25 Jul Fri Team returns from the Shri Debates"
  },
  {
    "page": 3,
    "line_no": 22,
    "text": "25 Jul Fri Students leave for IPSC Dramatics Fest at EHIS, Indore"
  },
  {
    "page": 3,
    "line_no": 23,
    "text": "26 Jul Sat The Doon School Chess Tournament begins"
  },
  {
    "page": 3,
    "line_no": 24,
    "text": "26 Jul Sat Inter-school Math Competition SIGMA"
  },
  {
    "page": 3,
    "line_no": 25,
    "text": "26 Jul Sat Inter-school Science competition ALPHA"
  },
  {
    "page": 3,
    "line_no": 26,
    "text": "26 Jul Sat Shanti Swaroop Essay Contest begins"
  },
  {
    "page": 4,
    "line_no": 1,
    "text": "27 Jul Sun OUTING"
  },
  {
    "page": 4,
    "line_no": 2,
    "text": "27 Jul Sun School team returns from IPSC Basketball"
  },
  {
    "page": 4,
    "line_no": 3,
    "text": "27 Jul Sun The Doon School Chess Tournament ends"
  },
  {
    "page": 4,
    "line_no": 4,
    "text": "27 Jul Sun Call Over - Jaipur House"
  },
  {
    "page": 4,
    "line_no": 5,
    "text": "28 Jul Mon Inter-house Football begins"
  },
  {
    "page": 4,
    "line_no": 6,
    "text": "29 Jul Tue Housemasters' Council Meeting"
  },
  {
    "page": 4,
    "line_no": 7,
    "text": "29 Jul Tue International Tiger Day"
  },
  {
    "page": 4,
    "line_no": 8,
    "text": "30 Jul Wed SPIC MACAY performance (TBC)"
  },
  {
    "page": 4,
    "line_no": 9,
    "text": "30 Jul Wed Students return from IPSC Dramatics Fest"
  },
  {
    "page": 4,
    "line_no": 10,
    "text": "31 Jul Thu IBDP (Cohort 2026) - Eco IA 1 Final Submission"
  },
  {
    "page": 4,
    "line_no": 11,
    "text": "31 Jul Thu Inter-house Hindi Debates (Sr) - Third round"
  },
  {
    "page": 4,
    "line_no": 12,
    "text": "31 Jul Thu Team leaves for the Jaipur Debates at Neerja Modi School, Jaipur"
  },
  {
    "page": 4,
    "line_no": 13,
    "text": "1 Aug Fri IPSC Visual Art begins (TBC)"
  },
  {
    "page": 4,
    "line_no": 14,
    "text": "1 Aug Fri Artist in Residence (Debating and Public Speaking) begins"
  },
  {
    "page": 4,
    "line_no": 15,
    "text": "2 Aug Sat Young Entrepreneurs’ Conference begins"
  },
  {
    "page": 4,
    "line_no": 16,
    "text": "2 Aug Sat Manorite TT invitational, St. Georges College Mussoorie (TBC)"
  },
  {
    "page": 4,
    "line_no": 17,
    "text": "2 Aug Sat School team leaves for IPSC Music at Sanskaar Valley School, Bhopal"
  },
  {
    "page": 4,
    "line_no": 18,
    "text": "3 Aug Sun NO OUTING"
  },
  {
    "page": 4,
    "line_no": 19,
    "text": "3 Aug Sun Manorite TT invitational, St. Georges College Mussoorie (TBC)"
  },
  {
    "page": 4,
    "line_no": 20,
    "text": "3 Aug Sun Call Over - Kashmir House"
  },
  {
    "page": 4,
    "line_no": 21,
    "text": "3 Aug Sun Young Entrepreneurs’ Conference ends"
  },
  {
    "page": 4,
    "line_no": 22,
    "text": "4 Aug Mon Academic Council Meeting"
  },
  {
    "page": 4,
    "line_no": 23,
    "text": "4 Aug Mon RLSS Camp begins"
  },
  {
    "page": 4,
    "line_no": 24,
    "text": "4 Aug Mon Team returns from the Jaipur Debates"
  },
  {
    "page": 4,
    "line_no": 25,
    "text": "5 Aug Tue The OASIS Badminton Invitational Begins (TBC)"
  },
  {
    "page": 4,
    "line_no": 26,
    "text": "6 Aug Wed Inter-house Hindi Debates (Sr) - Fourth round"
  },
  {
    "page": 5,
    "line_no": 1,
    "text": "8 Aug Fri Inter-house Hindi Debates (Sr) - Semifinals"
  },
  {
    "page": 5,
    "line_no": 2,
    "text": "8 Aug Fri International Chemistry Quiz"
  },
  {
    "page": 5,
    "line_no": 3,
    "text": "9 Aug Sat PD session for staff"
  },
  {
    "page": 5,
    "line_no": 4,
    "text": "9 Aug Sat Tutorial Meeting Lunch"
  },
  {
    "page": 5,
    "line_no": 5,
    "text": "9 Aug Sat Artist in Residence (Debating and Public Speaking) ends"
  },
  {
    "page": 5,
    "line_no": 6,
    "text": "9 Aug Sat Inter-house Hindi Debates (Sr) - Finals"
  },
  {
    "page": 5,
    "line_no": 7,
    "text": "9 Aug Sat RLSS Camp ends"
  },
  {
    "page": 5,
    "line_no": 8,
    "text": "9 Aug Sat DSOBS vs School Football Team (TBC)"
  },
  {
    "page": 5,
    "line_no": 9,
    "text": "10 Aug Sun Doon School Admission Test"
  },
  {
    "page": 5,
    "line_no": 10,
    "text": "10 Aug Sun OUTING"
  },
  {
    "page": 5,
    "line_no": 11,
    "text": "10 Aug Sun School team returns from IPSC Music"
  },
  {
    "page": 5,
    "line_no": 12,
    "text": "10 Aug Sun Call Over - Oberoi House"
  },
  {
    "page": 5,
    "line_no": 13,
    "text": "11 Aug Mon D form Hindi Debating league begins"
  },
  {
    "page": 5,
    "line_no": 14,
    "text": "11 Aug Mon School team leaves for IPSC Dance at RKK Girls' School, Jodhpur"
  },
  {
    "page": 5,
    "line_no": 15,
    "text": "14 Aug Thu School Council meeting"
  },
  {
    "page": 5,
    "line_no": 16,
    "text": "15 Aug Fri Independence Day"
  },
  {
    "page": 5,
    "line_no": 17,
    "text": "16 Aug Sat Janmashtami"
  },
  {
    "page": 5,
    "line_no": 18,
    "text": "16 Aug Sat The Doon School Model United Nations Conference begins"
  },
  {
    "page": 5,
    "line_no": 19,
    "text": "17 Aug Sun NO OUTING"
  },
  {
    "page": 5,
    "line_no": 20,
    "text": "17 Aug Sun School team leaves for IPSC Badminton and IPSC Table Tennis at Emerald Heights International School Indore"
  },
  {
    "page": 5,
    "line_no": 21,
    "text": "17 Aug Sun D form Hindi Debating league ends"
  },
  {
    "page": 5,
    "line_no": 22,
    "text": "17 Aug Sun Call Over - Tata House"
  },
  {
    "page": 5,
    "line_no": 23,
    "text": "18 Aug Mon The Doon School Model United Nations Conference ends"
  },
  {
    "page": 5,
    "line_no": 24,
    "text": "18 Aug Mon School team returns from IPSC Dance"
  },
  {
    "page": 6,
    "line_no": 1,
    "text": "19 Aug Tue Round Square Regional Conference at Sunbeam School, Lahartara begins"
  },
  {
    "page": 6,
    "line_no": 2,
    "text": "20 Aug Wed TOEFL Test"
  },
  {
    "page": 6,
    "line_no": 3,
    "text": "20 Aug Wed Uttarakhand state Inter-school shooting championship"
  },
  {
    "page": 6,
    "line_no": 4,
    "text": "21 Aug Thu IBDP Program Development Meeting"
  },
  {
    "page": 6,
    "line_no": 5,
    "text": "22 Aug Fri The Doon School Junior Football Tournament begins"
  },
  {
    "page": 6,
    "line_no": 6,
    "text": "22 Aug Fri School team returns from IPSC Badminton and IPSC Table Tennis"
  },
  {
    "page": 6,
    "line_no": 7,
    "text": "23 Aug Sat Parent Teacher Meeting – SC Form, S Form, and A Form"
  },
  {
    "page": 6,
    "line_no": 8,
    "text": "23 Aug Sat SAT exam"
  },
  {
    "page": 6,
    "line_no": 9,
    "text": "23 Aug Sat Round Square Regional Conference ends"
  },
  {
    "page": 6,
    "line_no": 10,
    "text": "23 Aug Sat MUN Training - D and C Form"
  },
  {
    "page": 6,
    "line_no": 11,
    "text": "24 Aug Sun OUTING"
  },
  {
    "page": 6,
    "line_no": 12,
    "text": "24 Aug Sun Call Over - Hyderabad House"
  },
  {
    "page": 6,
    "line_no": 13,
    "text": "25 Aug Mon Artist in Residence (Art) ends"
  },
  {
    "page": 6,
    "line_no": 14,
    "text": "25 Aug Mon Hindustani Instrumental workshop begins"
  },
  {
    "page": 6,
    "line_no": 15,
    "text": "26 Aug Tue Council meetings (Study, Pastoral, Tech, Co-curricular, IAYP)"
  },
  {
    "page": 6,
    "line_no": 16,
    "text": "26 Aug Tue Final Submission for Shanti Swaroop Essay Contest"
  },
  {
    "page": 6,
    "line_no": 17,
    "text": "26 Aug Tue College Fair"
  },
  {
    "page": 6,
    "line_no": 18,
    "text": "27 Aug Wed Hindustani Instrumental workshop ends"
  },
  {
    "page": 6,
    "line_no": 19,
    "text": "28 Aug Thu Kamla Jeevan Debates, Chuckerbutty Memorial Debates"
  },
  {
    "page": 6,
    "line_no": 20,
    "text": "28 Aug Thu The Doon School Quiz & JEDI begins"
  },
  {
    "page": 6,
    "line_no": 21,
    "text": "28 Aug Thu Pracheen Kala Kendra Theory Examination (TBC)"
  },
  {
    "page": 6,
    "line_no": 22,
    "text": "29 Aug Fri The Doon School Junior Football Tournament ends"
  },
  {
    "page": 7,
    "line_no": 1,
    "text": "31 Aug Sun NO OUTING"
  },
  {
    "page": 7,
    "line_no": 2,
    "text": "31 Aug Sun Kamla Jeevan Debates, Chuckerbutty Memorial Debates, The Doon School Quiz & JEDI ends"
  },
  {
    "page": 7,
    "line_no": 3,
    "text": "31 Aug Sun Call Over - Jaipur House"
  },
  {
    "page": 7,
    "line_no": 4,
    "text": "1 Sep Mon Audition for Vikram Seth Statesmen Poetry Competition"
  },
  {
    "page": 7,
    "line_no": 5,
    "text": "1 Sep Mon Workshop on Executive Function Skills and Exam Stress Management - A form"
  },
  {
    "page": 7,
    "line_no": 6,
    "text": "1 Sep Mon Inter-house Hockey begins"
  },
  {
    "page": 7,
    "line_no": 7,
    "text": "2 Sep Tue Workshop on Executive Function Skills and Exam Stress Management - SC form"
  },
  {
    "page": 7,
    "line_no": 8,
    "text": "2 Sep Tue Inter-house Music Competition: Piano Solo, Classical Vocal, Percussion Orchestra"
  },
  {
    "page": 7,
    "line_no": 9,
    "text": "3 Sep Wed Inter-house Music Competition: Indian Orchestra and Choir"
  },
  {
    "page": 7,
    "line_no": 10,
    "text": "4 Sep Thu Library Council meeting"
  },
  {
    "page": 7,
    "line_no": 11,
    "text": "4 Sep Thu Delegation leaves for Bangkok for the WSC Global round"
  },
  {
    "page": 7,
    "line_no": 12,
    "text": "4 Sep Thu Delegation leaves for IPSC MUN at Lawrence School, Sanawar"
  },
  {
    "page": 7,
    "line_no": 13,
    "text": "6 Sep Sat Parent Teacher Meeting – B Form, C Form, and D Form"
  },
  {
    "page": 7,
    "line_no": 14,
    "text": "7 Sep Sun OUTING"
  },
  {
    "page": 7,
    "line_no": 15,
    "text": "7 Sep Sun IOQM"
  },
  {
    "page": 7,
    "line_no": 16,
    "text": "7 Sep Sun Call Over - Kashmir House"
  },
  {
    "page": 7,
    "line_no": 17,
    "text": "7 Sep Sun Delegation returns from IPSC MUN"
  },
  {
    "page": 7,
    "line_no": 18,
    "text": "8 Sep Mon Joint meeting of Housemasters' and Academic Council"
  },
  {
    "page": 7,
    "line_no": 19,
    "text": "8 Sep Mon Meraki 2025- Interschool Design Competition (TBC)"
  },
  {
    "page": 7,
    "line_no": 20,
    "text": "8 Sep Mon Math-around-us-week begins"
  },
  {
    "page": 8,
    "line_no": 1,
    "text": "21 Sep Sun NO OUTING"
  },
  {
    "page": 8,
    "line_no": 2,
    "text": "21 Sep Sun Call Over - Tata House"
  },
  {
    "page": 8,
    "line_no": 3,
    "text": "22 Sep Mon September Assessment begins"
  },
  {
    "page": 8,
    "line_no": 4,
    "text": "26 Sep Fri RSIC Dubai ends"
  },
  {
    "page": 8,
    "line_no": 5,
    "text": "27 Sep Sat September Assessment ends"
  },
  {
    "page": 8,
    "line_no": 6,
    "text": "27 Sep Sat French Exchange - Lycee Ozanam visits TDS"
  },
  {
    "page": 8,
    "line_no": 7,
    "text": "28 Sep Sun NO OUTING"
  },
  {
    "page": 8,
    "line_no": 8,
    "text": "28 Sep Sun Call Over - Hyderabad House"
  },
  {
    "page": 8,
    "line_no": 9,
    "text": "28 Sep Sun Inter-house Triathlon"
  },
  {
    "page": 8,
    "line_no": 10,
    "text": "28 Sep Sun House Feast"
  },
  {
    "page": 8,
    "line_no": 11,
    "text": "29 Sep Mon Housemasters' Council Meeting"
  },
  {
    "page": 8,
    "line_no": 12,
    "text": "29 Sep Mon School team leaves for IPSC Shooting (U-19) & IPSC Tennis (U-14 & 17) at Daly College, Indore"
  },
  {
    "page": 8,
    "line_no": 13,
    "text": "30 Sep Tue Council meetings (Study, Pastoral, Tech, Co-curricular, IAYP)"
  },
  {
    "page": 8,
    "line_no": 14,
    "text": "1 Oct Wed TOEFL Test"
  },
  {
    "page": 8,
    "line_no": 15,
    "text": "2 Oct Thu Gandhi Jayanti"
  },
  {
    "page": 8,
    "line_no": 16,
    "text": "2 Oct Thu Dussehra"
  },
  {
    "page": 8,
    "line_no": 17,
    "text": "3 Oct Fri School Council Meeting"
  },
  {
    "page": 8,
    "line_no": 18,
    "text": "3 Oct Fri Theatre Workshop begins"
  },
  {
    "page": 9,
    "line_no": 1,
    "text": "4 Oct Sat SAT exam"
  },
  {
    "page": 9,
    "line_no": 2,
    "text": "4 Oct Sat Report Card meeting for A and SC form"
  },
  {
    "page": 9,
    "line_no": 3,
    "text": "4 Oct Sat School team returns from IPSC Shooting & IPSC Tennis"
  },
  {
    "page": 9,
    "line_no": 4,
    "text": "5 Oct Sun NO OUTING"
  },
  {
    "page": 9,
    "line_no": 5,
    "text": "5 Oct Sun Theatre Workshop ends"
  },
  {
    "page": 9,
    "line_no": 6,
    "text": "5 Oct Sun Call Over - Jaipur House"
  },
  {
    "page": 9,
    "line_no": 7,
    "text": "5 Oct Sun School team leaves for IPSC Football at Daly College, Indore"
  },
  {
    "page": 9,
    "line_no": 8,
    "text": "5 Oct Sun French Exchange ends"
  },
  {
    "page": 9,
    "line_no": 9,
    "text": "6 Oct Mon Academic Council meeting"
  },
  {
    "page": 9,
    "line_no": 10,
    "text": "9 Oct Thu Inter-house Athletics begins"
  },
  {
    "page": 9,
    "line_no": 11,
    "text": "9 Oct Thu School team leaves for Basketball tournament at Mayo College (TBC)"
  },
  {
    "page": 9,
    "line_no": 12,
    "text": "11 Oct Sat Tutorial Meeting"
  },
  {
    "page": 9,
    "line_no": 13,
    "text": "11 Oct Sat School team returns from IPSC Football"
  },
  {
    "page": 9,
    "line_no": 14,
    "text": "12 Oct Sun NO OUTING"
  },
  {
    "page": 9,
    "line_no": 15,
    "text": "12 Oct Sun Call Over - Kashmir House"
  },
  {
    "page": 9,
    "line_no": 16,
    "text": "16 Oct Thu Founder's Day - DS 90"
  },
  {
    "page": 9,
    "line_no": 17,
    "text": "16 Oct Thu Inter-house Athletics ends"
  },
  {
    "page": 10,
    "line_no": 1,
    "text": "17 Oct Fri Founder's Day - DS 90"
  },
  {
    "page": 10,
    "line_no": 2,
    "text": "18 Oct Sat Founder's Day - DS 90"
  },
  {
    "page": 10,
    "line_no": 3,
    "text": "18 Oct Sat Students leave for Founder's Night Out"
  },
  {
    "page": 10,
    "line_no": 4,
    "text": "20 Oct Mon Deepawali"
  },
  {
    "page": 10,
    "line_no": 5,
    "text": "22 Oct Wed Team leaves for the India Today Debates at Vasant Valley School, Delhi (TBC)"
  },
  {
    "page": 10,
    "line_no": 6,
    "text": "22 Oct Wed Green Olympiad (TBC)"
  },
  {
    "page": 10,
    "line_no": 7,
    "text": "23 Oct Thu Students return from Founder's Night Out"
  },
  {
    "page": 10,
    "line_no": 8,
    "text": "25 Oct Sat Tutorial Meeting"
  },
  {
    "page": 10,
    "line_no": 9,
    "text": "25 Oct Sat ACT exam"
  },
  {
    "page": 10,
    "line_no": 10,
    "text": "26 Oct Sun NO OUTING"
  },
  {
    "page": 10,
    "line_no": 11,
    "text": "26 Oct Sun Call Over - Oberoi House"
  },
  {
    "page": 10,
    "line_no": 12,
    "text": "27 Oct Mon Options at 14+"
  },
  {
    "page": 10,
    "line_no": 13,
    "text": "28 Oct Tue PSAT exam"
  },
  {
    "page": 10,
    "line_no": 14,
    "text": "28 Oct Tue School team leaves for IPSC Hockey at B K Birla Centre for Education, Pune"
  },
  {
    "page": 10,
    "line_no": 15,
    "text": "28 Oct Tue Options at 14+"
  },
  {
    "page": 10,
    "line_no": 16,
    "text": "29 Oct Wed FIT 1 & FIT 2 - German Certificate Exams"
  },
  {
    "page": 10,
    "line_no": 17,
    "text": "30 Oct Thu IBDP Program Development Meeting"
  },
  {
    "page": 10,
    "line_no": 18,
    "text": "30 Oct Thu School team leaves for IPSC Basketball (Under 14, Boys) at Birla Public School, Pilani (TBC)"
  },
  {
    "page": 11,
    "line_no": 1,
    "text": "31 Oct Fri Housemasters' Council Meeting"
  },
  {
    "page": 11,
    "line_no": 2,
    "text": "31 Oct Fri Rock School Music Examination"
  },
  {
    "page": 11,
    "line_no": 3,
    "text": "31 Oct Fri Tareekh: Paper presentation"
  },
  {
    "page": 11,
    "line_no": 4,
    "text": "1 Nov Sat PD session for staff"
  },
  {
    "page": 11,
    "line_no": 5,
    "text": "1 Nov Sat Industrial trip for B form Commercial Application students (TBC)"
  },
  {
    "page": 11,
    "line_no": 6,
    "text": "1 Nov Sat District Athletics Meet (TBC)"
  },
  {
    "page": 11,
    "line_no": 7,
    "text": "1 Nov Sat House Feast"
  },
  {
    "page": 11,
    "line_no": 8,
    "text": "2 Nov Sun NO OUTING"
  },
  {
    "page": 11,
    "line_no": 9,
    "text": "2 Nov Sun School team returns from IPSC Hockey"
  },
  {
    "page": 11,
    "line_no": 10,
    "text": "2 Nov Sun School teams leaves for IPSC Cricket Emerald Heights International School, Indore"
  },
  {
    "page": 11,
    "line_no": 11,
    "text": "2 Nov Sun School team leaves for IPSC Boxing to BPS, Pilani (TBC)"
  },
  {
    "page": 11,
    "line_no": 12,
    "text": "2 Nov Sun Call Over - Tata House"
  },
  {
    "page": 11,
    "line_no": 13,
    "text": "3 Nov Mon Academic Council meeting"
  },
  {
    "page": 11,
    "line_no": 14,
    "text": "3 Nov Mon Inter-house Basketball begins"
  },
  {
    "page": 11,
    "line_no": 15,
    "text": "4 Nov Tue Poetry Appreciation Evening"
  },
  {
    "page": 11,
    "line_no": 16,
    "text": "4 Nov Tue International Informatics Olympiad"
  },
  {
    "page": 11,
    "line_no": 17,
    "text": "4 Nov Tue Options at 16+"
  },
  {
    "page": 11,
    "line_no": 18,
    "text": "5 Nov Wed Guru Nanak Jayanti"
  },
  {
    "page": 11,
    "line_no": 19,
    "text": "6 Nov Thu School Council Meeting"
  },
  {
    "page": 11,
    "line_no": 20,
    "text": "6 Nov Thu KULTURA FESTA"
  },
  {
    "page": 11,
    "line_no": 21,
    "text": "6 Nov Thu Last date for submission of poems for Hindi Poetry Competition"
  },
  {
    "page": 11,
    "line_no": 22,
    "text": "7 Nov Fri Library Council meeting"
  },
  {
    "page": 11,
    "line_no": 23,
    "text": "7 Nov Fri B.P. Chandola Memorial Hindi Essay Prize Contest"
  },
  {
    "page": 11,
    "line_no": 24,
    "text": "7 Nov Fri International Artificial Intelligence Olympiad"
  },
  {
    "page": 12,
    "line_no": 1,
    "text": "8 Nov Sat SAT exam"
  },
  {
    "page": 12,
    "line_no": 2,
    "text": "8 Nov Sat PD session for staff"
  },
  {
    "page": 12,
    "line_no": 3,
    "text": "8 Nov Sat Tutorial Meeting"
  },
  {
    "page": 12,
    "line_no": 4,
    "text": "8 Nov Sat Trinity Music Theory Examination"
  },
  {
    "page": 12,
    "line_no": 5,
    "text": "8 Nov Sat Open Day-Visit for prospective parents"
  },
  {
    "page": 12,
    "line_no": 6,
    "text": "9 Nov Sun NO OUTING"
  },
  {
    "page": 12,
    "line_no": 7,
    "text": "9 Nov Sun School teams returns from IPSC Cricket"
  },
  {
    "page": 12,
    "line_no": 8,
    "text": "9 Nov Sun Call Over - Hyderabad House"
  },
  {
    "page": 12,
    "line_no": 9,
    "text": "10 Nov Mon Council meetings (Study, Pastoral, Tech, Co-curricular, IAYP)"
  },
  {
    "page": 12,
    "line_no": 10,
    "text": "10 Nov Mon Last date for submission of Hindi Short Stories"
  },
  {
    "page": 12,
    "line_no": 11,
    "text": "10 Nov Mon Navin Chandra Best Hindi debater’s cup begins"
  },
  {
    "page": 12,
    "line_no": 12,
    "text": "11 Nov Tue Inter-house Boxing begins"
  },
  {
    "page": 12,
    "line_no": 13,
    "text": "12 Nov Wed Navin Chandra Best Hindi Debater’s cup ends"
  },
  {
    "page": 12,
    "line_no": 14,
    "text": "13 Nov Thu Inter-house Boxing ends"
  },
  {
    "page": 12,
    "line_no": 15,
    "text": "15 Nov Sat November Trials/Pre-board 1 begins"
  },
  {
    "page": 12,
    "line_no": 16,
    "text": "15 Nov Sat IBDP (Cohort 2026) - Final IO (English LangLit HL/SL) begins"
  },
  {
    "page": 12,
    "line_no": 17,
    "text": "16 Nov Sun NO OUTING"
  },
  {
    "page": 12,
    "line_no": 18,
    "text": "19 Nov Wed IBDP (Cohort 2026)- Final IO (English LangLit HL/SL) ends"
  },
  {
    "page": 12,
    "line_no": 19,
    "text": "20 Nov Thu IBDP (Cohort 2026) - Final IO For Hindi A begins"
  },
  {
    "page": 12,
    "line_no": 20,
    "text": "23 Nov Sun NO OUTING"
  },
  {
    "page": 13,
    "line_no": 1,
    "text": "25 Nov Tue IBDP (Cohort 2026) - Final IO For Hindi A ends"
  },
  {
    "page": 13,
    "line_no": 2,
    "text": "27 Nov Thu November Trials/Pre-Board 1 end"
  },
  {
    "page": 13,
    "line_no": 3,
    "text": "28 Nov Fri Trinity Rock & Pop Examination Venue Music School"
  },
  {
    "page": 13,
    "line_no": 4,
    "text": "28 Nov Fri Housemasters' Council meeting"
  },
  {
    "page": 13,
    "line_no": 5,
    "text": "28 Nov Fri Inter-house Cross-country"
  },
  {
    "page": 13,
    "line_no": 6,
    "text": "28 Nov Fri Yearbook photographs"
  },
  {
    "page": 13,
    "line_no": 7,
    "text": "29 Nov Sat End of Term Assembly"
  },
  {
    "page": 13,
    "line_no": 8,
    "text": "30 Nov Sun Winter Vacations begin & Students leave for home"
  },
  {
    "page": 13,
    "line_no": 9,
    "text": "30 Nov Sun Winter Expedition begins"
  },
  {
    "page": 13,
    "line_no": 10,
    "text": "30 Nov Sun School team leaves for IPSC Athletics at Emerald Heights International School, Indore"
  },
  {
    "page": 13,
    "line_no": 11,
    "text": "1 Dec Mon Academic Council meeting"
  },
  {
    "page": 13,
    "line_no": 12,
    "text": "2 Dec Tue BSAI The Doon School Technology Conclave"
  },
  {
    "page": 13,
    "line_no": 13,
    "text": "3 Dec Wed BSAI The Doon School Technology Conclave"
  },
  {
    "page": 13,
    "line_no": 14,
    "text": "4 Dec Thu School team returns from IPSC Athletics"
  },
  {
    "page": 13,
    "line_no": 15,
    "text": "6 Dec Sat SAT exam"
  },
  {
    "page": 13,
    "line_no": 16,
    "text": "16 - 20 Dec RSC Assam Valley"
  },
  {
    "page": 13,
    "line_no": 17,
    "text": "11 - 19 Dec French Exchange at Lycee Ozanam, Lille"
  }
]